bruker_utils/__init__.py
bruker_utils/_version.py
bruker_utils-0.0.2.dist-info/LICENSE
bruker_utils-0.0.2.dist-info/METADATA
bruker_utils-0.0.2.dist-info/WHEEL
bruker_utils-0.0.2.dist-info/top_level.txt
bruker_utils-0.0.2.dist-info/RECORD
