Metadata-Version: 2.1
Name: bruker_utils
Version: 0.0.2
Summary: bruker_utils: Helper functions for handling Bruker NMR data.
Home-page: https://github.com/5hulse/bruker_utils
Author: Simon Hulse
Author-email: simon.hulse@chem.ox.ac.uk
Classifier: Programming Language :: Python :: 3.6
Classifier: License :: OSI Approved :: MIT License
Classifier: Operating System :: OS Independent
Classifier: Topic :: Scientific/Engineering
Requires-Python: >=3.6
License-File: LICENSE
Requires-Dist: numpy
